{
  "Unknown Test Framework": {
    "coverage": {
    },
    "timestamp": 1532126461
  },
  "Unit Tests": {
    "coverage": {
      "/Users/abdullaqudrat/turing/1module/projects/black_thursday_project/black_thursday/lib/item_repository.rb": [
        1,
        1,
        1,
        1,
        null,
        1,
        1,
        1,
        null,
        1,
        14,
        14,
        14,
        null,
        null,
        1,
        14,
        19138,
        null,
        null,
        null,
        1,
        9,
        null,
        null,
        null,
        null,
        null,
        null,
        null,
        null,
        1,
        3,
        1368,
        null,
        null,
        null,
        1,
        2,
        2,
        2734,
        null,
        null,
        null,
        1,
        null,
        1,
        1367,
        null,
        null,
        null,
        1,
        1,
        1367,
        null,
        null,
        null,
        1,
        1,
        1,
        1367,
        null,
        null,
        null,
        1,
        2,
        2,
        2,
        2,
        null,
        null,
        1,
        3,
        4101,
        null,
        3,
        3,
        null,
        null,
        1,
        1,
        1,
        1,
        1,
        null,
        null,
        1,
        1,
        null,
        null,
        1,
        0,
        null,
        null
      ],
      "/Users/abdullaqudrat/turing/1module/projects/black_thursday_project/black_thursday/lib/item.rb": [
        1,
        1,
        1,
        null,
        1,
        1,
        null,
        null,
        null,
        1,
        null,
        null,
        null,
        null,
        1,
        19140,
        19140,
        19140,
        19140,
        19140,
        19140,
        19140,
        null,
        null,
        1,
        0,
        null,
        null
      ],
      "/Users/abdullaqudrat/turing/1module/projects/black_thursday_project/black_thursday/lib/repo_method_helper.rb": [
        1,
        null,
        1,
        7,
        6842,
        null,
        null,
        null,
        null
      ]
    },
    "timestamp": 1532539114
  }
}
