{
  "Unknown Test Framework": {
    "coverage": {
    },
    "timestamp": 1532126461
  },
  "Unit Tests": {
    "coverage": {
      "/Users/danielmulitauopele/Turing/1Module/black_thursday_project/black_thursday/lib/item_repository.rb": [
        1,
        1,
        1,
        null,
        1,
        1,
        null,
        1,
        1,
        1,
        1,
        null,
        null,
        1,
        1,
        1367,
        null,
        null,
        null,
        1,
        1,
        1,
        null,
        null
      ],
      "/Users/danielmulitauopele/Turing/1Module/black_thursday_project/black_thursday/lib/item.rb": [
        1,
        1,
        null,
        null,
        1,
        1367,
        1367,
        null,
        null
      ]
    },
    "timestamp": 1532219059
  }
}
